ancp/__init__.py
ancp/client.py
ancp/subscriber.py
PyANCP-0.1.7.dist-info/LICENSE
PyANCP-0.1.7.dist-info/METADATA
PyANCP-0.1.7.dist-info/WHEEL
PyANCP-0.1.7.dist-info/top_level.txt
PyANCP-0.1.7.dist-info/zip-safe
PyANCP-0.1.7.dist-info/RECORD
