Metadata-Version: 2.1
Name: PyANCP
Version: 0.1.7
Summary: Python ANCP (RFC 6320) Client and Library
Home-page: https://github.com/GIC-de/PyANCP
Author: Christian Giese (GIC-de)
License: MIT
Classifier: Programming Language :: Python :: 2.7
Classifier: Programming Language :: Python :: 3.8
Classifier: Programming Language :: Python :: 3.9
Classifier: Programming Language :: Python :: 3.10
License-File: LICENSE
Requires-Dist: future
